{
  "metadata": {
    "edge_count": 103,
    "node_count": 35,
    "threshold": 0.05,
    "normalized": true,
    "description": "Jaccard similarity with minimum 0.05 similarity score"
  },
  "nodes": [
    {
      "id": "0xcd719c599ebc51193c5c97cbe188f43c8c4c8745",
      "name": "Lost Discs",
      "size": 211,
      "community": 0,
      "hierarchical": 1,
      "kmeans": 3,
      "degree_centrality": 0.714286,
      "betweenness_centrality": 0.013676,
      "eigenvector_centrality": 0.07293
    },
    {
      "id": "0x8af130613bd8a7c714a43def3454a0f5ddf2344e",
      "name": "Meco Nads",
      "size": 939,
      "community": 0,
      "hierarchical": 3,
      "kmeans": 1,
      "degree_centrality": 0.693878,
      "betweenness_centrality": 0.05428,
      "eigenvector_centrality": 0.174344
    },
    {
      "id": "0x3a9454c1b4c84d1861bb1209a647c834d137b442",
      "name": "The10kSquad",
      "size": 916,
      "community": 0,
      "hierarchical": 3,
      "kmeans": 1,
      "degree_centrality": 0.612245,
      "betweenness_centrality": 0.0,
      "eigenvector_centrality": 0.146751
    },
    {
      "id": "0x46c66c40711a2953d1768926e53134c7ab272cd5",
      "name": "Blench Pass",
      "size": 291,
      "community": 0,
      "hierarchical": 3,
      "kmeans": 3,
      "degree_centrality": 0.653061,
      "betweenness_centrality": 0.0,
      "eigenvector_centrality": 0.127752
    },
    {
      "id": "0xfe5b5af24280af7ea190a41d0240fe30c46f1c40",
      "name": "HaHa x Mongang Pass",
      "size": 716,
      "community": 0,
      "hierarchical": 1,
      "kmeans": 3,
      "degree_centrality": 0.653061,
      "betweenness_centrality": 0.0,
      "eigenvector_centrality": 0.114999
    },
    {
      "id": "0xc5c9425d733b9f769593bd2814b6301916f91271",
      "name": "Purple Frens",
      "size": 933,
      "community": 0,
      "hierarchical": 4,
      "kmeans": 1,
      "degree_centrality": 0.632653,
      "betweenness_centrality": 0.0,
      "eigenvector_centrality": 0.155725
    },
    {
      "id": "0x7370a0a9e9a833bcd071b38fc25184e7afb57aff",
      "name": "Chog Pass",
      "size": 93,
      "community": 0,
      "hierarchical": 0,
      "kmeans": 0,
      "degree_centrality": 0.632653,
      "betweenness_centrality": 0.367396,
      "eigenvector_centrality": 0.013453
    },
    {
      "id": "0x6ed438b2a8eff227e7e54b5324926941b140eea0",
      "name": "Blocknads",
      "size": 919,
      "community": 0,
      "hierarchical": 8,
      "kmeans": 6,
      "degree_centrality": 0.632653,
      "betweenness_centrality": 0.0,
      "eigenvector_centrality": 0.307895
    },
    {
      "id": "0xd60c64487d581d5eb2b15f221bd6d8187a9a4aef",
      "name": "Meowwnads | OG Pass",
      "size": 1,
      "community": 0,
      "hierarchical": 0,
      "kmeans": 0,
      "degree_centrality": 0.122449,
      "betweenness_centrality": 0.012105,
      "eigenvector_centrality": 0.000301
    },
    {
      "id": "0xa568cabe34c8ca0d2a8671009ae0f6486a314425",
      "name": "Meowwnads",
      "size": 1,
      "community": 0,
      "hierarchical": 0,
      "kmeans": 0,
      "degree_centrality": 0.040816,
      "betweenness_centrality": 0.0,
      "eigenvector_centrality": 0.000196
    },
    {
      "id": "0x6341c537a6fc563029d8e8caa87da37f227358f4",
      "name": "Molandaks Mint Pass",
      "size": 547,
      "community": 0,
      "hierarchical": 2,
      "kmeans": 3,
      "degree_centrality": 0.714286,
      "betweenness_centrality": 0.062713,
      "eigenvector_centrality": 0.125524
    },
    {
      "id": "0xd20ef03e432208af083c0fb4e401049f4f29949f",
      "name": "Lil chogstars Superstarlist Pass",
      "size": 895,
      "community": 0,
      "hierarchical": 3,
      "kmeans": 1,
      "degree_centrality": 0.632653,
      "betweenness_centrality": 0.0,
      "eigenvector_centrality": 0.184725
    },
    {
      "id": "0xff59f1e14c4f5522158a0cf029f94475ba469458",
      "name": "Mystery Token",
      "size": 1,
      "community": 0,
      "hierarchical": 0,
      "kmeans": 0,
      "degree_centrality": 0.061224,
      "betweenness_centrality": 0.000935,
      "eigenvector_centrality": 0.000175
    },
    {
      "id": "0xb981a81b45f604f82bd502a35c6dbe25dd2e8b8d",
      "name": "RealNads Premint Pass",
      "size": 844,
      "community": 0,
      "hierarchical": 3,
      "kmeans": 3,
      "degree_centrality": 0.693878,
      "betweenness_centrality": 0.0,
      "eigenvector_centrality": 0.141525
    },
    {
      "id": "0xbc8f6824fde979848ad97a52bced2d6ca1842a68",
      "name": "Momo",
      "size": 540,
      "community": 0,
      "hierarchical": 3,
      "kmeans": 1,
      "degree_centrality": 0.673469,
      "betweenness_centrality": 0.023231,
      "eigenvector_centrality": 0.156475
    },
    {
      "id": "0xf105209830ebcaef5f1b85fb3e7f44256d1af2e3",
      "name": "Moyaking Pass",
      "size": 689,
      "community": 0,
      "hierarchical": 3,
      "kmeans": 1,
      "degree_centrality": 0.653061,
      "betweenness_centrality": 0.0,
      "eigenvector_centrality": 0.175788
    },
    {
      "id": "0x87e1f1824c9356733a25d6bed6b9c87a3b31e107",
      "name": "Spikes",
      "size": 930,
      "community": 0,
      "hierarchical": 5,
      "kmeans": 2,
      "degree_centrality": 0.653061,
      "betweenness_centrality": 0.0,
      "eigenvector_centrality": 0.261742
    },
    {
      "id": "0x49d54cd9ca8c5ecadbb346dc6b4e31549f34e405",
      "name": "Overnads: Whitelist Pass",
      "size": 1,
      "community": 0,
      "hierarchical": 0,
      "kmeans": 0,
      "degree_centrality": 0.040816,
      "betweenness_centrality": 0.0,
      "eigenvector_centrality": 0.000196
    },
    {
      "id": "0x2b9ee0a88d69eef1cffe3ea330165e17fd976c3c",
      "name": "r3tardv3rs3",
      "size": 274,
      "community": 0,
      "hierarchical": 3,
      "kmeans": 1,
      "degree_centrality": 0.653061,
      "betweenness_centrality": 0.0,
      "eigenvector_centrality": 0.146148
    },
    {
      "id": "0x0f2f2da004acc38f05858f9dbc0320db64c1b6c9",
      "name": "Foggy",
      "size": 866,
      "community": 0,
      "hierarchical": 5,
      "kmeans": 2,
      "degree_centrality": 0.632653,
      "betweenness_centrality": 0.0,
      "eigenvector_centrality": 0.252928
    },
    {
      "id": "0x4e88056e13de12bde065589e501033227d8188e6",
      "name": "The Daks Fantasies",
      "size": 1,
      "community": 0,
      "hierarchical": 0,
      "kmeans": 0,
      "degree_centrality": 0.122449,
      "betweenness_centrality": 0.012105,
      "eigenvector_centrality": 0.000301
    },
    {
      "id": "0xbb406139138401f4475ca5cf2d7152847159eb7a",
      "name": "SpiKeys",
      "size": 172,
      "community": 0,
      "hierarchical": 0,
      "kmeans": 0,
      "degree_centrality": 0.653061,
      "betweenness_centrality": 0.111863,
      "eigenvector_centrality": 0.020997
    },
    {
      "id": "0x84db60168be10fb2ae274ea84e24cb22ffe11ddd",
      "name": "Mondana Baddies: Baddie Eye",
      "size": 1,
      "community": 0,
      "hierarchical": 0,
      "kmeans": 0,
      "degree_centrality": 0.061224,
      "betweenness_centrality": 0.000935,
      "eigenvector_centrality": 0.000175
    },
    {
      "id": "0xe047e7501ac25d3003a8da147648b088d9df0b07",
      "name": "LootGO Looties",
      "size": 331,
      "community": 0,
      "hierarchical": 1,
      "kmeans": 3,
      "degree_centrality": 0.673469,
      "betweenness_centrality": 0.035809,
      "eigenvector_centrality": 0.09837
    },
    {
      "id": "0x8827a10506653af9de490e160ad134e6293d3b47",
      "name": "Monad Nurse",
      "size": 108,
      "community": 0,
      "hierarchical": 1,
      "kmeans": 3,
      "degree_centrality": 0.632653,
      "betweenness_centrality": 0.0,
      "eigenvector_centrality": 0.07464
    },
    {
      "id": "0xed52e0d80f4e7b295df5e622b55eff22d262f6ed",
      "name": "r3tards",
      "size": 316,
      "community": 0,
      "hierarchical": 3,
      "kmeans": 1,
      "degree_centrality": 0.632653,
      "betweenness_centrality": 0.0,
      "eigenvector_centrality": 0.191651
    },
    {
      "id": "0x78ed9a576519024357ab06d9834266a04c9634b7",
      "name": "TheDaks",
      "size": 941,
      "community": 0,
      "hierarchical": 9,
      "kmeans": 5,
      "degree_centrality": 0.632653,
      "betweenness_centrality": 0.0,
      "eigenvector_centrality": 0.332315
    },
    {
      "id": "0x88bbcba96a52f310497774e7fd5ebadf0ece21fb",
      "name": "Chewy",
      "size": 785,
      "community": 0,
      "hierarchical": 5,
      "kmeans": 2,
      "degree_centrality": 0.653061,
      "betweenness_centrality": 0.034014,
      "eigenvector_centrality": 0.229192
    },
    {
      "id": "0x5a21b0f4a4f9b54e16282b6ed5ad014b3c77186f",
      "name": "La Mouch",
      "size": 935,
      "community": 0,
      "hierarchical": 3,
      "kmeans": 1,
      "degree_centrality": 0.653061,
      "betweenness_centrality": 0.0,
      "eigenvector_centrality": 0.174247
    },
    {
      "id": "0xe6b5427b174344fd5cb1e3d5550306b0055473c6",
      "name": "Chogs Mystery Chest",
      "size": 797,
      "community": 0,
      "hierarchical": 7,
      "kmeans": 4,
      "degree_centrality": 0.673469,
      "betweenness_centrality": 0.066327,
      "eigenvector_centrality": 0.309877
    },
    {
      "id": "0xa980f072bc06d67faec2b03a8ada0d6c9d0da9f8",
      "name": "Legacy Eggs",
      "size": 851,
      "community": 0,
      "hierarchical": 6,
      "kmeans": 7,
      "degree_centrality": 0.632653,
      "betweenness_centrality": 0.0,
      "eigenvector_centrality": 0.28198
    },
    {
      "id": "0xd6421e9c72199e971e5a3cde09214054e1216cd2",
      "name": "Mondana Baddies Eye Chain",
      "size": 150,
      "community": 0,
      "hierarchical": 1,
      "kmeans": 3,
      "degree_centrality": 0.673469,
      "betweenness_centrality": 0.011366,
      "eigenvector_centrality": 0.102476
    },
    {
      "id": "0x7da93750de078bfbbab0dd30635448e9ec7fb8f0",
      "name": "EGGcellent",
      "size": 564,
      "community": 0,
      "hierarchical": 3,
      "kmeans": 3,
      "degree_centrality": 0.714286,
      "betweenness_centrality": 0.04812,
      "eigenvector_centrality": 0.136187
    },
    {
      "id": "0xb0a663cf4853e67221fee43322fda402e21debfc",
      "name": "Llamao Genesis",
      "size": 1,
      "community": 0,
      "hierarchical": 0,
      "kmeans": 0,
      "degree_centrality": 0.122449,
      "betweenness_centrality": 0.012105,
      "eigenvector_centrality": 0.000301
    },
    {
      "id": "0xe8f0635591190fb626f9d13c49b60626561ed145",
      "name": "Skrumpets",
      "size": 492,
      "community": 0,
      "hierarchical": 3,
      "kmeans": 1,
      "degree_centrality": 0.632653,
      "betweenness_centrality": 0.0,
      "eigenvector_centrality": 0.175625
    }
  ],
  "edges": [
    {
      "source": "0xd20ef03e432208af083c0fb4e401049f4f29949f",
      "target": "0xe6b5427b174344fd5cb1e3d5550306b0055473c6",
      "weight": 0.10013,
      "source_name": "Lil chogstars Superstarlist Pass",
      "target_name": "Chogs Mystery Chest"
    },
    {
      "source": "0xd20ef03e432208af083c0fb4e401049f4f29949f",
      "target": "0xbc8f6824fde979848ad97a52bced2d6ca1842a68",
      "weight": 0.063751,
      "source_name": "Lil chogstars Superstarlist Pass",
      "target_name": "Momo"
    },
    {
      "source": "0xd20ef03e432208af083c0fb4e401049f4f29949f",
      "target": "0xe8f0635591190fb626f9d13c49b60626561ed145",
      "weight": 0.055556,
      "source_name": "Lil chogstars Superstarlist Pass",
      "target_name": "Skrumpets"
    },
    {
      "source": "0xd20ef03e432208af083c0fb4e401049f4f29949f",
      "target": "0xed52e0d80f4e7b295df5e622b55eff22d262f6ed",
      "weight": 0.050304,
      "source_name": "Lil chogstars Superstarlist Pass",
      "target_name": "r3tards"
    },
    {
      "source": "0xd20ef03e432208af083c0fb4e401049f4f29949f",
      "target": "0x78ed9a576519024357ab06d9834266a04c9634b7",
      "weight": 0.055172,
      "source_name": "Lil chogstars Superstarlist Pass",
      "target_name": "TheDaks"
    },
    {
      "source": "0xe6b5427b174344fd5cb1e3d5550306b0055473c6",
      "target": "0xbc8f6824fde979848ad97a52bced2d6ca1842a68",
      "weight": 0.067039,
      "source_name": "Chogs Mystery Chest",
      "target_name": "Momo"
    },
    {
      "source": "0xe6b5427b174344fd5cb1e3d5550306b0055473c6",
      "target": "0xe8f0635591190fb626f9d13c49b60626561ed145",
      "weight": 0.088682,
      "source_name": "Chogs Mystery Chest",
      "target_name": "Skrumpets"
    },
    {
      "source": "0xe6b5427b174344fd5cb1e3d5550306b0055473c6",
      "target": "0xed52e0d80f4e7b295df5e622b55eff22d262f6ed",
      "weight": 0.10089,
      "source_name": "Chogs Mystery Chest",
      "target_name": "r3tards"
    },
    {
      "source": "0xe6b5427b174344fd5cb1e3d5550306b0055473c6",
      "target": "0x87e1f1824c9356733a25d6bed6b9c87a3b31e107",
      "weight": 0.093038,
      "source_name": "Chogs Mystery Chest",
      "target_name": "Spikes"
    },
    {
      "source": "0xe6b5427b174344fd5cb1e3d5550306b0055473c6",
      "target": "0xd6421e9c72199e971e5a3cde09214054e1216cd2",
      "weight": 0.067644,
      "source_name": "Chogs Mystery Chest",
      "target_name": "Mondana Baddies Eye Chain"
    },
    {
      "source": "0xe6b5427b174344fd5cb1e3d5550306b0055473c6",
      "target": "0x2b9ee0a88d69eef1cffe3ea330165e17fd976c3c",
      "weight": 0.100719,
      "source_name": "Chogs Mystery Chest",
      "target_name": "r3tardv3rs3"
    },
    {
      "source": "0xe6b5427b174344fd5cb1e3d5550306b0055473c6",
      "target": "0x8af130613bd8a7c714a43def3454a0f5ddf2344e",
      "weight": 0.115681,
      "source_name": "Chogs Mystery Chest",
      "target_name": "Meco Nads"
    },
    {
      "source": "0xe6b5427b174344fd5cb1e3d5550306b0055473c6",
      "target": "0x46c66c40711a2953d1768926e53134c7ab272cd5",
      "weight": 0.056311,
      "source_name": "Chogs Mystery Chest",
      "target_name": "Blench Pass"
    },
    {
      "source": "0xe6b5427b174344fd5cb1e3d5550306b0055473c6",
      "target": "0xf105209830ebcaef5f1b85fb3e7f44256d1af2e3",
      "weight": 0.058405,
      "source_name": "Chogs Mystery Chest",
      "target_name": "Moyaking Pass"
    },
    {
      "source": "0xe6b5427b174344fd5cb1e3d5550306b0055473c6",
      "target": "0xa980f072bc06d67faec2b03a8ada0d6c9d0da9f8",
      "weight": 0.110512,
      "source_name": "Chogs Mystery Chest",
      "target_name": "Legacy Eggs"
    },
    {
      "source": "0xe6b5427b174344fd5cb1e3d5550306b0055473c6",
      "target": "0x6ed438b2a8eff227e7e54b5324926941b140eea0",
      "weight": 0.099295,
      "source_name": "Chogs Mystery Chest",
      "target_name": "Blocknads"
    },
    {
      "source": "0xe6b5427b174344fd5cb1e3d5550306b0055473c6",
      "target": "0x78ed9a576519024357ab06d9834266a04c9634b7",
      "weight": 0.118404,
      "source_name": "Chogs Mystery Chest",
      "target_name": "TheDaks"
    },
    {
      "source": "0xe6b5427b174344fd5cb1e3d5550306b0055473c6",
      "target": "0x0f2f2da004acc38f05858f9dbc0320db64c1b6c9",
      "weight": 0.089777,
      "source_name": "Chogs Mystery Chest",
      "target_name": "Foggy"
    },
    {
      "source": "0xe6b5427b174344fd5cb1e3d5550306b0055473c6",
      "target": "0x5a21b0f4a4f9b54e16282b6ed5ad014b3c77186f",
      "weight": 0.052248,
      "source_name": "Chogs Mystery Chest",
      "target_name": "La Mouch"
    },
    {
      "source": "0xe6b5427b174344fd5cb1e3d5550306b0055473c6",
      "target": "0x88bbcba96a52f310497774e7fd5ebadf0ece21fb",
      "weight": 0.073999,
      "source_name": "Chogs Mystery Chest",
      "target_name": "Chewy"
    },
    {
      "source": "0xbc8f6824fde979848ad97a52bced2d6ca1842a68",
      "target": "0xe8f0635591190fb626f9d13c49b60626561ed145",
      "weight": 0.063918,
      "source_name": "Momo",
      "target_name": "Skrumpets"
    },
    {
      "source": "0xbc8f6824fde979848ad97a52bced2d6ca1842a68",
      "target": "0xed52e0d80f4e7b295df5e622b55eff22d262f6ed",
      "weight": 0.064677,
      "source_name": "Momo",
      "target_name": "r3tards"
    },
    {
      "source": "0xbc8f6824fde979848ad97a52bced2d6ca1842a68",
      "target": "0x2b9ee0a88d69eef1cffe3ea330165e17fd976c3c",
      "weight": 0.075297,
      "source_name": "Momo",
      "target_name": "r3tardv3rs3"
    },
    {
      "source": "0xbc8f6824fde979848ad97a52bced2d6ca1842a68",
      "target": "0x7da93750de078bfbbab0dd30635448e9ec7fb8f0",
      "weight": 0.06256,
      "source_name": "Momo",
      "target_name": "EGGcellent"
    },
    {
      "source": "0xbc8f6824fde979848ad97a52bced2d6ca1842a68",
      "target": "0x6ed438b2a8eff227e7e54b5324926941b140eea0",
      "weight": 0.058781,
      "source_name": "Momo",
      "target_name": "Blocknads"
    },
    {
      "source": "0xbc8f6824fde979848ad97a52bced2d6ca1842a68",
      "target": "0x78ed9a576519024357ab06d9834266a04c9634b7",
      "weight": 0.051847,
      "source_name": "Momo",
      "target_name": "TheDaks"
    },
    {
      "source": "0xe8f0635591190fb626f9d13c49b60626561ed145",
      "target": "0xed52e0d80f4e7b295df5e622b55eff22d262f6ed",
      "weight": 0.102319,
      "source_name": "Skrumpets",
      "target_name": "r3tards"
    },
    {
      "source": "0xe8f0635591190fb626f9d13c49b60626561ed145",
      "target": "0x87e1f1824c9356733a25d6bed6b9c87a3b31e107",
      "weight": 0.051775,
      "source_name": "Skrumpets",
      "target_name": "Spikes"
    },
    {
      "source": "0xe8f0635591190fb626f9d13c49b60626561ed145",
      "target": "0xd6421e9c72199e971e5a3cde09214054e1216cd2",
      "weight": 0.059406,
      "source_name": "Skrumpets",
      "target_name": "Mondana Baddies Eye Chain"
    },
    {
      "source": "0xe8f0635591190fb626f9d13c49b60626561ed145",
      "target": "0x2b9ee0a88d69eef1cffe3ea330165e17fd976c3c",
      "weight": 0.114993,
      "source_name": "Skrumpets",
      "target_name": "r3tardv3rs3"
    },
    {
      "source": "0xe8f0635591190fb626f9d13c49b60626561ed145",
      "target": "0x46c66c40711a2953d1768926e53134c7ab272cd5",
      "weight": 0.051007,
      "source_name": "Skrumpets",
      "target_name": "Blench Pass"
    },
    {
      "source": "0xe8f0635591190fb626f9d13c49b60626561ed145",
      "target": "0xa980f072bc06d67faec2b03a8ada0d6c9d0da9f8",
      "weight": 0.059984,
      "source_name": "Skrumpets",
      "target_name": "Legacy Eggs"
    },
    {
      "source": "0xe8f0635591190fb626f9d13c49b60626561ed145",
      "target": "0x6ed438b2a8eff227e7e54b5324926941b140eea0",
      "weight": 0.070561,
      "source_name": "Skrumpets",
      "target_name": "Blocknads"
    },
    {
      "source": "0xe8f0635591190fb626f9d13c49b60626561ed145",
      "target": "0x78ed9a576519024357ab06d9834266a04c9634b7",
      "weight": 0.068606,
      "source_name": "Skrumpets",
      "target_name": "TheDaks"
    },
    {
      "source": "0xed52e0d80f4e7b295df5e622b55eff22d262f6ed",
      "target": "0x87e1f1824c9356733a25d6bed6b9c87a3b31e107",
      "weight": 0.070447,
      "source_name": "r3tards",
      "target_name": "Spikes"
    },
    {
      "source": "0xed52e0d80f4e7b295df5e622b55eff22d262f6ed",
      "target": "0xd6421e9c72199e971e5a3cde09214054e1216cd2",
      "weight": 0.114833,
      "source_name": "r3tards",
      "target_name": "Mondana Baddies Eye Chain"
    },
    {
      "source": "0xed52e0d80f4e7b295df5e622b55eff22d262f6ed",
      "target": "0x2b9ee0a88d69eef1cffe3ea330165e17fd976c3c",
      "weight": 0.128107,
      "source_name": "r3tards",
      "target_name": "r3tardv3rs3"
    },
    {
      "source": "0xed52e0d80f4e7b295df5e622b55eff22d262f6ed",
      "target": "0x8827a10506653af9de490e160ad134e6293d3b47",
      "weight": 0.12766,
      "source_name": "r3tards",
      "target_name": "Monad Nurse"
    },
    {
      "source": "0xed52e0d80f4e7b295df5e622b55eff22d262f6ed",
      "target": "0x46c66c40711a2953d1768926e53134c7ab272cd5",
      "weight": 0.064912,
      "source_name": "r3tards",
      "target_name": "Blench Pass"
    },
    {
      "source": "0xed52e0d80f4e7b295df5e622b55eff22d262f6ed",
      "target": "0xa980f072bc06d67faec2b03a8ada0d6c9d0da9f8",
      "weight": 0.069661,
      "source_name": "r3tards",
      "target_name": "Legacy Eggs"
    },
    {
      "source": "0xed52e0d80f4e7b295df5e622b55eff22d262f6ed",
      "target": "0x6ed438b2a8eff227e7e54b5324926941b140eea0",
      "weight": 0.074848,
      "source_name": "r3tards",
      "target_name": "Blocknads"
    },
    {
      "source": "0xed52e0d80f4e7b295df5e622b55eff22d262f6ed",
      "target": "0x78ed9a576519024357ab06d9834266a04c9634b7",
      "weight": 0.113375,
      "source_name": "r3tards",
      "target_name": "TheDaks"
    },
    {
      "source": "0xed52e0d80f4e7b295df5e622b55eff22d262f6ed",
      "target": "0x0f2f2da004acc38f05858f9dbc0320db64c1b6c9",
      "weight": 0.12894,
      "source_name": "r3tards",
      "target_name": "Foggy"
    },
    {
      "source": "0xed52e0d80f4e7b295df5e622b55eff22d262f6ed",
      "target": "0x88bbcba96a52f310497774e7fd5ebadf0ece21fb",
      "weight": 0.062741,
      "source_name": "r3tards",
      "target_name": "Chewy"
    },
    {
      "source": "0x87e1f1824c9356733a25d6bed6b9c87a3b31e107",
      "target": "0xa980f072bc06d67faec2b03a8ada0d6c9d0da9f8",
      "weight": 0.091299,
      "source_name": "Spikes",
      "target_name": "Legacy Eggs"
    },
    {
      "source": "0x87e1f1824c9356733a25d6bed6b9c87a3b31e107",
      "target": "0x6ed438b2a8eff227e7e54b5324926941b140eea0",
      "weight": 0.093436,
      "source_name": "Spikes",
      "target_name": "Blocknads"
    },
    {
      "source": "0x87e1f1824c9356733a25d6bed6b9c87a3b31e107",
      "target": "0x78ed9a576519024357ab06d9834266a04c9634b7",
      "weight": 0.100588,
      "source_name": "Spikes",
      "target_name": "TheDaks"
    },
    {
      "source": "0x87e1f1824c9356733a25d6bed6b9c87a3b31e107",
      "target": "0x0f2f2da004acc38f05858f9dbc0320db64c1b6c9",
      "weight": 0.071599,
      "source_name": "Spikes",
      "target_name": "Foggy"
    },
    {
      "source": "0x87e1f1824c9356733a25d6bed6b9c87a3b31e107",
      "target": "0x88bbcba96a52f310497774e7fd5ebadf0ece21fb",
      "weight": 0.078616,
      "source_name": "Spikes",
      "target_name": "Chewy"
    },
    {
      "source": "0xd6421e9c72199e971e5a3cde09214054e1216cd2",
      "target": "0x2b9ee0a88d69eef1cffe3ea330165e17fd976c3c",
      "weight": 0.073418,
      "source_name": "Mondana Baddies Eye Chain",
      "target_name": "r3tardv3rs3"
    },
    {
      "source": "0xd6421e9c72199e971e5a3cde09214054e1216cd2",
      "target": "0x8827a10506653af9de490e160ad134e6293d3b47",
      "weight": 0.121739,
      "source_name": "Mondana Baddies Eye Chain",
      "target_name": "Monad Nurse"
    },
    {
      "source": "0xd6421e9c72199e971e5a3cde09214054e1216cd2",
      "target": "0x46c66c40711a2953d1768926e53134c7ab272cd5",
      "weight": 0.070388,
      "source_name": "Mondana Baddies Eye Chain",
      "target_name": "Blench Pass"
    },
    {
      "source": "0xd6421e9c72199e971e5a3cde09214054e1216cd2",
      "target": "0x6ed438b2a8eff227e7e54b5324926941b140eea0",
      "weight": 0.056324,
      "source_name": "Mondana Baddies Eye Chain",
      "target_name": "Blocknads"
    },
    {
      "source": "0xd6421e9c72199e971e5a3cde09214054e1216cd2",
      "target": "0x78ed9a576519024357ab06d9834266a04c9634b7",
      "weight": 0.056147,
      "source_name": "Mondana Baddies Eye Chain",
      "target_name": "TheDaks"
    },
    {
      "source": "0xd6421e9c72199e971e5a3cde09214054e1216cd2",
      "target": "0x0f2f2da004acc38f05858f9dbc0320db64c1b6c9",
      "weight": 0.058333,
      "source_name": "Mondana Baddies Eye Chain",
      "target_name": "Foggy"
    },
    {
      "source": "0x2b9ee0a88d69eef1cffe3ea330165e17fd976c3c",
      "target": "0x8827a10506653af9de490e160ad134e6293d3b47",
      "weight": 0.088319,
      "source_name": "r3tardv3rs3",
      "target_name": "Monad Nurse"
    },
    {
      "source": "0x2b9ee0a88d69eef1cffe3ea330165e17fd976c3c",
      "target": "0x46c66c40711a2953d1768926e53134c7ab272cd5",
      "weight": 0.06403,
      "source_name": "r3tardv3rs3",
      "target_name": "Blench Pass"
    },
    {
      "source": "0x2b9ee0a88d69eef1cffe3ea330165e17fd976c3c",
      "target": "0xa980f072bc06d67faec2b03a8ada0d6c9d0da9f8",
      "weight": 0.06032,
      "source_name": "r3tardv3rs3",
      "target_name": "Legacy Eggs"
    },
    {
      "source": "0x2b9ee0a88d69eef1cffe3ea330165e17fd976c3c",
      "target": "0x6ed438b2a8eff227e7e54b5324926941b140eea0",
      "weight": 0.055752,
      "source_name": "r3tardv3rs3",
      "target_name": "Blocknads"
    },
    {
      "source": "0x2b9ee0a88d69eef1cffe3ea330165e17fd976c3c",
      "target": "0x78ed9a576519024357ab06d9834266a04c9634b7",
      "weight": 0.062992,
      "source_name": "r3tardv3rs3",
      "target_name": "TheDaks"
    },
    {
      "source": "0x2b9ee0a88d69eef1cffe3ea330165e17fd976c3c",
      "target": "0x0f2f2da004acc38f05858f9dbc0320db64c1b6c9",
      "weight": 0.051661,
      "source_name": "r3tardv3rs3",
      "target_name": "Foggy"
    },
    {
      "source": "0x84db60168be10fb2ae274ea84e24cb22ffe11ddd",
      "target": "0xff59f1e14c4f5522158a0cf029f94475ba469458",
      "weight": 1.0,
      "source_name": "Mondana Baddies: Baddie Eye",
      "target_name": "Mystery Token"
    },
    {
      "source": "0xcd719c599ebc51193c5c97cbe188f43c8c4c8745",
      "target": "0xe047e7501ac25d3003a8da147648b088d9df0b07",
      "weight": 0.054475,
      "source_name": "Lost Discs",
      "target_name": "LootGO Looties"
    },
    {
      "source": "0xcd719c599ebc51193c5c97cbe188f43c8c4c8745",
      "target": "0x46c66c40711a2953d1768926e53134c7ab272cd5",
      "weight": 0.054622,
      "source_name": "Lost Discs",
      "target_name": "Blench Pass"
    },
    {
      "source": "0xcd719c599ebc51193c5c97cbe188f43c8c4c8745",
      "target": "0xf105209830ebcaef5f1b85fb3e7f44256d1af2e3",
      "weight": 0.062574,
      "source_name": "Lost Discs",
      "target_name": "Moyaking Pass"
    },
    {
      "source": "0xcd719c599ebc51193c5c97cbe188f43c8c4c8745",
      "target": "0x7da93750de078bfbbab0dd30635448e9ec7fb8f0",
      "weight": 0.067493,
      "source_name": "Lost Discs",
      "target_name": "EGGcellent"
    },
    {
      "source": "0x49d54cd9ca8c5ecadbb346dc6b4e31549f34e405",
      "target": "0xa568cabe34c8ca0d2a8671009ae0f6486a314425",
      "weight": 1.0,
      "source_name": "Overnads: Whitelist Pass",
      "target_name": "Meowwnads"
    },
    {
      "source": "0x6341c537a6fc563029d8e8caa87da37f227358f4",
      "target": "0x8af130613bd8a7c714a43def3454a0f5ddf2344e",
      "weight": 0.073699,
      "source_name": "Molandaks Mint Pass",
      "target_name": "Meco Nads"
    },
    {
      "source": "0x6341c537a6fc563029d8e8caa87da37f227358f4",
      "target": "0xc5c9425d733b9f769593bd2814b6301916f91271",
      "weight": 0.147287,
      "source_name": "Molandaks Mint Pass",
      "target_name": "Purple Frens"
    },
    {
      "source": "0xb981a81b45f604f82bd502a35c6dbe25dd2e8b8d",
      "target": "0xf105209830ebcaef5f1b85fb3e7f44256d1af2e3",
      "weight": 0.055785,
      "source_name": "RealNads Premint Pass",
      "target_name": "Moyaking Pass"
    },
    {
      "source": "0x8827a10506653af9de490e160ad134e6293d3b47",
      "target": "0x46c66c40711a2953d1768926e53134c7ab272cd5",
      "weight": 0.055556,
      "source_name": "Monad Nurse",
      "target_name": "Blench Pass"
    },
    {
      "source": "0xe047e7501ac25d3003a8da147648b088d9df0b07",
      "target": "0xf105209830ebcaef5f1b85fb3e7f44256d1af2e3",
      "weight": 0.056995,
      "source_name": "LootGO Looties",
      "target_name": "Moyaking Pass"
    },
    {
      "source": "0x46c66c40711a2953d1768926e53134c7ab272cd5",
      "target": "0xf105209830ebcaef5f1b85fb3e7f44256d1af2e3",
      "weight": 0.062907,
      "source_name": "Blench Pass",
      "target_name": "Moyaking Pass"
    },
    {
      "source": "0x46c66c40711a2953d1768926e53134c7ab272cd5",
      "target": "0x7da93750de078bfbbab0dd30635448e9ec7fb8f0",
      "weight": 0.05948,
      "source_name": "Blench Pass",
      "target_name": "EGGcellent"
    },
    {
      "source": "0x46c66c40711a2953d1768926e53134c7ab272cd5",
      "target": "0x6ed438b2a8eff227e7e54b5324926941b140eea0",
      "weight": 0.063269,
      "source_name": "Blench Pass",
      "target_name": "Blocknads"
    },
    {
      "source": "0x46c66c40711a2953d1768926e53134c7ab272cd5",
      "target": "0x78ed9a576519024357ab06d9834266a04c9634b7",
      "weight": 0.055698,
      "source_name": "Blench Pass",
      "target_name": "TheDaks"
    },
    {
      "source": "0xc5c9425d733b9f769593bd2814b6301916f91271",
      "target": "0x88bbcba96a52f310497774e7fd5ebadf0ece21fb",
      "weight": 0.050122,
      "source_name": "Purple Frens",
      "target_name": "Chewy"
    },
    {
      "source": "0xf105209830ebcaef5f1b85fb3e7f44256d1af2e3",
      "target": "0x7da93750de078bfbbab0dd30635448e9ec7fb8f0",
      "weight": 0.067291,
      "source_name": "Moyaking Pass",
      "target_name": "EGGcellent"
    },
    {
      "source": "0xf105209830ebcaef5f1b85fb3e7f44256d1af2e3",
      "target": "0xa980f072bc06d67faec2b03a8ada0d6c9d0da9f8",
      "weight": 0.055517,
      "source_name": "Moyaking Pass",
      "target_name": "Legacy Eggs"
    },
    {
      "source": "0xf105209830ebcaef5f1b85fb3e7f44256d1af2e3",
      "target": "0xfe5b5af24280af7ea190a41d0240fe30c46f1c40",
      "weight": 0.053223,
      "source_name": "Moyaking Pass",
      "target_name": "HaHa x Mongang Pass"
    },
    {
      "source": "0xf105209830ebcaef5f1b85fb3e7f44256d1af2e3",
      "target": "0x6ed438b2a8eff227e7e54b5324926941b140eea0",
      "weight": 0.068439,
      "source_name": "Moyaking Pass",
      "target_name": "Blocknads"
    },
    {
      "source": "0xf105209830ebcaef5f1b85fb3e7f44256d1af2e3",
      "target": "0x78ed9a576519024357ab06d9834266a04c9634b7",
      "weight": 0.058442,
      "source_name": "Moyaking Pass",
      "target_name": "TheDaks"
    },
    {
      "source": "0x7370a0a9e9a833bcd071b38fc25184e7afb57aff",
      "target": "0xbb406139138401f4475ca5cf2d7152847159eb7a",
      "weight": 0.113445,
      "source_name": "Chog Pass",
      "target_name": "SpiKeys"
    },
    {
      "source": "0x7da93750de078bfbbab0dd30635448e9ec7fb8f0",
      "target": "0xfe5b5af24280af7ea190a41d0240fe30c46f1c40",
      "weight": 0.056106,
      "source_name": "EGGcellent",
      "target_name": "HaHa x Mongang Pass"
    },
    {
      "source": "0x7da93750de078bfbbab0dd30635448e9ec7fb8f0",
      "target": "0x6ed438b2a8eff227e7e54b5324926941b140eea0",
      "weight": 0.056268,
      "source_name": "EGGcellent",
      "target_name": "Blocknads"
    },
    {
      "source": "0xa980f072bc06d67faec2b03a8ada0d6c9d0da9f8",
      "target": "0x6ed438b2a8eff227e7e54b5324926941b140eea0",
      "weight": 0.111111,
      "source_name": "Legacy Eggs",
      "target_name": "Blocknads"
    },
    {
      "source": "0xa980f072bc06d67faec2b03a8ada0d6c9d0da9f8",
      "target": "0x78ed9a576519024357ab06d9834266a04c9634b7",
      "weight": 0.118602,
      "source_name": "Legacy Eggs",
      "target_name": "TheDaks"
    },
    {
      "source": "0xa980f072bc06d67faec2b03a8ada0d6c9d0da9f8",
      "target": "0x0f2f2da004acc38f05858f9dbc0320db64c1b6c9",
      "weight": 0.095026,
      "source_name": "Legacy Eggs",
      "target_name": "Foggy"
    },
    {
      "source": "0xa980f072bc06d67faec2b03a8ada0d6c9d0da9f8",
      "target": "0x88bbcba96a52f310497774e7fd5ebadf0ece21fb",
      "weight": 0.078444,
      "source_name": "Legacy Eggs",
      "target_name": "Chewy"
    },
    {
      "source": "0x4e88056e13de12bde065589e501033227d8188e6",
      "target": "0xb0a663cf4853e67221fee43322fda402e21debfc",
      "weight": 1.0,
      "source_name": "The Daks Fantasies",
      "target_name": "Llamao Genesis"
    },
    {
      "source": "0x4e88056e13de12bde065589e501033227d8188e6",
      "target": "0xd60c64487d581d5eb2b15f221bd6d8187a9a4aef",
      "weight": 1.0,
      "source_name": "The Daks Fantasies",
      "target_name": "Meowwnads | OG Pass"
    },
    {
      "source": "0xb0a663cf4853e67221fee43322fda402e21debfc",
      "target": "0xd60c64487d581d5eb2b15f221bd6d8187a9a4aef",
      "weight": 1.0,
      "source_name": "Llamao Genesis",
      "target_name": "Meowwnads | OG Pass"
    },
    {
      "source": "0x6ed438b2a8eff227e7e54b5324926941b140eea0",
      "target": "0x78ed9a576519024357ab06d9834266a04c9634b7",
      "weight": 0.123867,
      "source_name": "Blocknads",
      "target_name": "TheDaks"
    },
    {
      "source": "0x6ed438b2a8eff227e7e54b5324926941b140eea0",
      "target": "0x0f2f2da004acc38f05858f9dbc0320db64c1b6c9",
      "weight": 0.085106,
      "source_name": "Blocknads",
      "target_name": "Foggy"
    },
    {
      "source": "0x6ed438b2a8eff227e7e54b5324926941b140eea0",
      "target": "0x5a21b0f4a4f9b54e16282b6ed5ad014b3c77186f",
      "weight": 0.054008,
      "source_name": "Blocknads",
      "target_name": "La Mouch"
    },
    {
      "source": "0x6ed438b2a8eff227e7e54b5324926941b140eea0",
      "target": "0x88bbcba96a52f310497774e7fd5ebadf0ece21fb",
      "weight": 0.090909,
      "source_name": "Blocknads",
      "target_name": "Chewy"
    },
    {
      "source": "0x78ed9a576519024357ab06d9834266a04c9634b7",
      "target": "0x0f2f2da004acc38f05858f9dbc0320db64c1b6c9",
      "weight": 0.100487,
      "source_name": "TheDaks",
      "target_name": "Foggy"
    },
    {
      "source": "0x78ed9a576519024357ab06d9834266a04c9634b7",
      "target": "0x5a21b0f4a4f9b54e16282b6ed5ad014b3c77186f",
      "weight": 0.061086,
      "source_name": "TheDaks",
      "target_name": "La Mouch"
    },
    {
      "source": "0x78ed9a576519024357ab06d9834266a04c9634b7",
      "target": "0x88bbcba96a52f310497774e7fd5ebadf0ece21fb",
      "weight": 0.110682,
      "source_name": "TheDaks",
      "target_name": "Chewy"
    },
    {
      "source": "0x78ed9a576519024357ab06d9834266a04c9634b7",
      "target": "0x3a9454c1b4c84d1861bb1209a647c834d137b442",
      "weight": 0.052721,
      "source_name": "TheDaks",
      "target_name": "The10kSquad"
    },
    {
      "source": "0x0f2f2da004acc38f05858f9dbc0320db64c1b6c9",
      "target": "0x5a21b0f4a4f9b54e16282b6ed5ad014b3c77186f",
      "weight": 0.051986,
      "source_name": "Foggy",
      "target_name": "La Mouch"
    },
    {
      "source": "0x0f2f2da004acc38f05858f9dbc0320db64c1b6c9",
      "target": "0x88bbcba96a52f310497774e7fd5ebadf0ece21fb",
      "weight": 0.052263,
      "source_name": "Foggy",
      "target_name": "Chewy"
    },
    {
      "source": "0x88bbcba96a52f310497774e7fd5ebadf0ece21fb",
      "target": "0x3a9454c1b4c84d1861bb1209a647c834d137b442",
      "weight": 0.051298,
      "source_name": "Chewy",
      "target_name": "The10kSquad"
    }
  ]
}